compas_grid/__init__.py
compas_grid/__main__.py
compas_grid/elements/__init__.py
compas_grid/elements/beam.py
compas_grid/elements/block.py
compas_grid/elements/cable.py
compas_grid/elements/column.py
compas_grid/elements/column_head.py
compas_grid/elements/cut.py
compas_grid/elements/plate.py
compas_grid/models/__init__.py
compas_grid/models/gridmodel.py
compas_grid-0.6.7.dist-info/LICENSE
compas_grid-0.6.7.dist-info/METADATA
compas_grid-0.6.7.dist-info/WHEEL
compas_grid-0.6.7.dist-info/top_level.txt
compas_grid-0.6.7.dist-info/RECORD
