Metadata-Version: 2.2
Name: compas_grid
Version: 0.6.7
Summary: Model of simple grid structures for multi-storey buildings.
Author-email: Petras Vestartas <petrasvestartas@gmail.com>
License: MIT License
Project-URL: Homepage, https://github.com/BRG-research/compas_grid.git
Project-URL: Documentation, https://github.com/BRG-research/compas_grid.git
Project-URL: Repository, https://github.com/BRG-research/compas_grid.git
Project-URL: Changelog, https://github.com/BRG-research/compas_grid/blob/main/CHANGELOG.md
Project-URL: Issues, https://github.com/BRG-research/compas_grid/issues
Project-URL: Forum, https://forum.compas-framework.org/
Classifier: Development Status :: 4 - Beta
Classifier: Topic :: Scientific/Engineering
Classifier: Operating System :: Unix
Classifier: Operating System :: POSIX
Classifier: Operating System :: Microsoft :: Windows
Classifier: Programming Language :: Python
Classifier: Programming Language :: Python :: 3
Classifier: Programming Language :: Python :: 3.9
Classifier: Programming Language :: Python :: 3.10
Classifier: Programming Language :: Python :: 3.11
Requires-Python: >=3.9
License-File: LICENSE
Requires-Dist: compas>=2
Requires-Dist: compas_viewer
Requires-Dist: compas_model
Provides-Extra: dev
Requires-Dist: attrs>=17.4; extra == "dev"
Requires-Dist: black>=22.12.0; extra == "dev"
Requires-Dist: bump-my-version; extra == "dev"
Requires-Dist: compas_invocations2; extra == "dev"
Requires-Dist: invoke>=0.14; extra == "dev"
Requires-Dist: ruff; extra == "dev"
Requires-Dist: sphinx_compas2_theme; extra == "dev"
Requires-Dist: twine; extra == "dev"
Requires-Dist: wheel; extra == "dev"
Requires-Dist: build; extra == "dev"
